kerasUtility/1.txt
kerasUtility/11.txt
kerasUtility/12.txt
kerasUtility/13.txt
kerasUtility/14.txt
kerasUtility/15.txt
kerasUtility/16.txt
kerasUtility/17.txt
kerasUtility/18.txt
kerasUtility/19.txt
kerasUtility/2.txt
kerasUtility/20.txt
kerasUtility/3.txt
kerasUtility/4.txt
kerasUtility/5.txt
kerasUtility/6.txt
kerasUtility/7.txt
kerasUtility/__init__.py
kerasUtility-2.0.dist-info/METADATA
kerasUtility-2.0.dist-info/WHEEL
kerasUtility-2.0.dist-info/top_level.txt
kerasUtility-2.0.dist-info/RECORD
