Metadata-Version: 2.1
Name: kerasUtility
Version: 2.0
Summary: Custom SKLearn package by N.K.Bhansodhe
Author: Parmish_Verma
Author-email: pcq02960@zslsz.com
